vectorm/__init__.py
vectorm/document.py
vectorm/filter.py
vectorm/migrate.py
vectorm/paginate.py
vectorm/py.typed
vectorm/store.py
vectorm/types.py
vectorm/backend/__init__.py
vectorm/backend/base.py
vectorm/backend/qdrant/__init__.py
vectorm/backend/qdrant/backend.py
vectorm/backend/qdrant/utils.py
vectorm/backend/qdrant/visitor.py
vectorm-0.1.2.dist-info/METADATA
vectorm-0.1.2.dist-info/WHEEL
vectorm-0.1.2.dist-info/licenses/LICENSE
vectorm-0.1.2.dist-info/RECORD
