Metadata-Version: 2.4
Name: vectorm
Version: 0.1.2
Summary: ORM layer for vector databases
Project-URL: repository, https://gitlab.com/wizrds/vectorm
Author-email: Timothy Pogue <me@pogue.dev>
License: ISC
License-File: LICENSE
Classifier: Programming Language :: Python :: 3 :: Only
Classifier: Programming Language :: Python :: 3.11
Classifier: Programming Language :: Python :: 3.12
Classifier: Programming Language :: Python :: 3.13
Requires-Python: >=3.11
Requires-Dist: numpy>=2.3.3
Requires-Dist: pydantic>=2.11.9
Provides-Extra: qdrant
Requires-Dist: qdrant-client>=1.15.1; extra == 'qdrant'
